README.md
setup.cfg
setup.py
tbc_adapter/__init__.py
tbc_adapter/adapter.py
tbc_adapter/p12_converter.py
tbc_adapter.egg-info/PKG-INFO
tbc_adapter.egg-info/SOURCES.txt
tbc_adapter.egg-info/dependency_links.txt
tbc_adapter.egg-info/not-zip-safe
tbc_adapter.egg-info/requires.txt
tbc_adapter.egg-info/top_level.txt