Metadata-Version: 1.1
Name: tbc-adapter
Version: 0.1
Summary: TBC payment gateway adapter
Home-page: https://github.com/Jambazishvili/tbc-adapter
Author: Giorgi (mecko) Jambazishvili
Author-email: giorgi.jambazishvili@gmail.com
License: MIT
Keywords: TBC,payment gateway,online payment
Platform: UNKNOWN
Classifier: Programming Language :: Python :: 3
Classifier: Intended Audience :: Developers
Classifier: Operating System :: OS Independent
